strazar/__init__.py
strazar-0.2.5.dist-info/DESCRIPTION.rst
strazar-0.2.5.dist-info/METADATA
strazar-0.2.5.dist-info/RECORD
strazar-0.2.5.dist-info/WHEEL
strazar-0.2.5.dist-info/metadata.json
strazar-0.2.5.dist-info/top_level.txt
