Metadata-Version: 2.0
Name: strazar
Version: 0.2.5
Summary: Automatic upstream dependency testing
Home-page: https://github.com/MrSenko/strazar
Author: Mr. Senko
Author-email: atodorov@mrsenko.com
License: BSD
Keywords: testing
Platform: UNKNOWN
Classifier: Development Status :: 4 - Beta
Classifier: Environment :: Web Environment
Classifier: Intended Audience :: Developers
Classifier: License :: OSI Approved :: BSD License
Classifier: Operating System :: OS Independent
Classifier: Programming Language :: Python
Requires-Dist: PyYAML
